onehouse_cli/__init__.py
onehouse_cli/cli.py
onehouse_cli/configure.py
onehouse_cli-0.1.2.dist-info/METADATA
onehouse_cli-0.1.2.dist-info/WHEEL
onehouse_cli-0.1.2.dist-info/entry_points.txt
onehouse_cli-0.1.2.dist-info/top_level.txt
onehouse_cli-0.1.2.dist-info/RECORD
