Metadata-Version: 2.4
Name: onehouse-cli
Version: 0.1.2
Summary: A command-line tool for executing SQL commands against the Onehouse API
Author-email: Sagar Lakshmipathy <18vidhyasagar@gmail.com>
License: Proprietary
Keywords: onehouse,cli
Classifier: Development Status :: 3 - Alpha
Classifier: Intended Audience :: Developers
Classifier: Programming Language :: Python :: 3
Classifier: Programming Language :: Python :: 3.7
Classifier: Programming Language :: Python :: 3.8
Classifier: Programming Language :: Python :: 3.9
Classifier: Programming Language :: Python :: 3.10
Classifier: Programming Language :: Python :: 3.11
Requires-Python: >=3.7
Requires-Dist: requests
